setup.py
OpenGLContext_qt/__init__.py
OpenGLContext_qt/qtcontext.py
OpenGLContext_qt/qtevents.py
OpenGLContext_qt.egg-info/PKG-INFO
OpenGLContext_qt.egg-info/SOURCES.txt
OpenGLContext_qt.egg-info/dependency_links.txt
OpenGLContext_qt.egg-info/top_level.txt