Metadata-Version: 1.1
Name: OpenGLContext-qt
Version: 1.0.0a3
Summary: PyQt4/PySide context for OpenGLContext
Home-page: http://pyopengl.sourceforge.net/context/
Author: Mike C. Fletcher
Author-email: mcfletch@users.sourceforge.net
License: BSD-style, see license.txt for details
Keywords: PyOpenGL,OpenGL,Context,OpenGLContext,render,3D,TrueType,text,VRML,VRML97,scenegraph
Platform: Linux
Classifier: License :: OSI Approved :: BSD License
Classifier: Programming Language :: Python
Classifier: Topic :: Software Development :: Libraries :: Python Modules
Classifier: Topic :: Multimedia :: Graphics :: 3D Rendering
Classifier: Intended Audience :: Developers
Classifier: Environment :: X11 Applications
